brx/__init__.py
brx_python-0.1.0.dist-info/METADATA
brx_python-0.1.0.dist-info/WHEEL
brx_python-0.1.0.dist-info/RECORD
